synapse_sso_proconnect/__init__.py
synapse_sso_proconnect/main.py
synapse_sso_proconnect-0.1.30.data/data/site-packages/synapse_sso_proconnect.pth
synapse_sso_proconnect-0.1.30.dist-info/METADATA
synapse_sso_proconnect-0.1.30.dist-info/WHEEL
synapse_sso_proconnect-0.1.30.dist-info/top_level.txt
synapse_sso_proconnect-0.1.30.dist-info/RECORD
